odoo/addons/purchase_procurement_run_buy_hook/README.rst
odoo/addons/purchase_procurement_run_buy_hook/__init__.py
odoo/addons/purchase_procurement_run_buy_hook/__manifest__.py
odoo/addons/purchase_procurement_run_buy_hook/hooks.py
odoo/addons/purchase_procurement_run_buy_hook/models/__init__.py
odoo/addons/purchase_procurement_run_buy_hook/models/procurement_rule.py
odoo/addons/purchase_procurement_run_buy_hook/static/description/icon.png
odoo/addons/purchase_procurement_run_buy_hook/tests/__init__.py
odoo/addons/purchase_procurement_run_buy_hook/tests/test_procurement_run_buy_hook.py
odoo11_addon_purchase_procurement_run_buy_hook-11.0.1.0.0.dist-info/DESCRIPTION.rst
odoo11_addon_purchase_procurement_run_buy_hook-11.0.1.0.0.dist-info/METADATA
odoo11_addon_purchase_procurement_run_buy_hook-11.0.1.0.0.dist-info/RECORD
odoo11_addon_purchase_procurement_run_buy_hook-11.0.1.0.0.dist-info/WHEEL
odoo11_addon_purchase_procurement_run_buy_hook-11.0.1.0.0.dist-info/metadata.json
odoo11_addon_purchase_procurement_run_buy_hook-11.0.1.0.0.dist-info/top_level.txt
